<?xml version="1.0" encoding="UTF-8"?>
<!DOCTYPE suite SYSTEM "https://testng.org/testng-1.0.dtd">

<suite name="System Suite" parallel="tests" thread-count="2">



  <listeners>
  <listener class-name="utility.Listernerclass"></listener>
  </listeners>
  
  
  <test  name="Testing with Chrome">
   
   <parameter name="browser" value="chrome"></parameter>
   <parameter name="url" value="https://www.amazon.in/"></parameter>
  
  
    <classes>
      <class name="bdd.AmazonProject1.Testcase1_LoginToAmazon"/>
      <class name="bdd.AmazonProject1.TestCase3_LoginandSearchProduct"/>
      <class name="bdd.AmazonProject1.Testcase2_LoginAndlogout"/>
      
      
      
    </classes>
  </test> <!-- Test -->
   <test  name="Testing with Edge">
   
   <parameter name="browser" value="edge"></parameter>
   <parameter name="url" value="https://www.amazon.in/"></parameter>
  
  
    <classes>
      <class name="bdd.AmazonProject1.Testcase1_LoginToAmazon"/>
      <class name="bdd.AmazonProject1.TestCase3_LoginandSearchProduct"/>
      <class name="bdd.AmazonProject1.Testcase2_LoginAndlogout"/>
     
      
      
    </classes>
  </test> <!-- Test -->
  
  
</suite> <!-- Suite -->
